{"errors":[],"quotes":[{"accountBalanceDetail":null,"estimatedItemizedDetail":{"discountSavingsText":null,"includedLineItems":[{"description":null,"displayedPerDay":false,"price":{"amount":60.00,"currencyCode":"USD"},"title":"$60 x 1 day","type":"VEHICLE_DAILY_TOTAL"}],"nonIncludedLineItems":[{"description":"Applies to all drivers under 25 years old","displayedPerDay":false,"price":null,"title":"Young driver fee","type":"YOUNG_DRIVER"},{"description":"Includes liability insurance and physical damage protection options; you’ll select a plan when you’re checking out","displayedPerDay":false,"price":null,"title":"Protection plan","type":"PROTECTION"},{"description":"This helps us run the Turo platform","displayedPerDay":false,"price":null,"title":"Trip fee","type":"TRIP_FEE"}],"priceDisplayType":"DAILY_WITH_EST_TOTAL","totalTripPrice":{"amount":60.00,"currencyCode":"USD"},"totalTripPriceBeforeDiscount":null,"vehicleDailyPrice":{"amount":60.00,"currencyCode":"USD"},"vehicleDailyPriceAfterDiscount":null},"quoteId":null,"tripDetail":null,"vehicleId":1325303},{"accountBalanceDetail":null,"estimatedItemizedDetail":{"discountSavingsText":null,"includedLineItems":[{"description":null,"displayedPerDay":false,"price":{"amount":70.00,"currencyCode":"USD"},"title":"$70 x 1 day","type":"VEHICLE_DAILY_TOTAL"}],"nonIncludedLineItems":[{"description":"Applies to all drivers under 25 years old","displayedPerDay":false,"price":null,"title":"Young driver fee","type":"YOUNG_DRIVER"},{"description":"Includes liability insurance and physical damage protection options; you’ll select a plan when you’re checking out","displayedPerDay":false,"price":null,"title":"Protection plan","type":"PROTECTION"},{"description":"This helps us run the Turo platform","displayedPerDay":false,"price":null,"title":"Trip fee","type":"TRIP_FEE"}],"priceDisplayType":"DAILY_WITH_EST_TOTAL","totalTripPrice":{"amount":70.00,"currencyCode":"USD"},"totalTripPriceBeforeDiscount":null,"vehicleDailyPrice":{"amount":70.00,"currencyCode":"USD"},"vehicleDailyPriceAfterDiscount":null},"quoteId":null,"tripDetail":null,"vehicleId":1706519},{"accountBalanceDetail":null,"estimatedItemizedDetail":{"discountSavingsText":null,"includedLineItems":[{"description":null,"displayedPerDay":false,"price":{"amount":100.00,"currencyCode":"USD"},"title":"$100 x 1 day","type":"VEHICLE_DAILY_TOTAL"}],"nonIncludedLineItems":[{"description":"Applies to all drivers under 25 years old","displayedPerDay":false,"price":null,"title":"Young driver fee","type":"YOUNG_DRIVER"},{"description":"Includes liability insurance and physical damage protection options; you’ll select a plan when you’re checking out","displayedPerDay":false,"price":null,"title":"Protection plan","type":"PROTECTION"},{"description":"This helps us run the Turo platform","displayedPerDay":false,"price":null,"title":"Trip fee","type":"TRIP_FEE"}],"priceDisplayType":"DAILY_WITH_EST_TOTAL","totalTripPrice":{"amount":100.00,"currencyCode":"USD"},"totalTripPriceBeforeDiscount":null,"vehicleDailyPrice":{"amount":100.00,"currencyCode":"USD"},"vehicleDailyPriceAfterDiscount":null},"quoteId":null,"tripDetail":null,"vehicleId":1877749},{"accountBalanceDetail":null,"estimatedItemizedDetail":{"discountSavingsText":null,"includedLineItems":[{"description":null,"displayedPerDay":false,"price":{"amount":80.00,"currencyCode":"USD"},"title":"$80 x 1 day","type":"VEHICLE_DAILY_TOTAL"}],"nonIncludedLineItems":[{"description":"Applies to all drivers under 25 years old","displayedPerDay":false,"price":null,"title":"Young driver fee","type":"YOUNG_DRIVER"},{"description":"Includes liability insurance and physical damage protection options; you’ll select a plan when you’re checking out","displayedPerDay":false,"price":null,"title":"Protection plan","type":"PROTECTION"},{"description":"This helps us run the Turo platform","displayedPerDay":false,"price":null,"title":"Trip fee","type":"TRIP_FEE"}],"priceDisplayType":"DAILY_WITH_EST_TOTAL","totalTripPrice":{"amount":80.00,"currencyCode":"USD"},"totalTripPriceBeforeDiscount":null,"vehicleDailyPrice":{"amount":80.00,"currencyCode":"USD"},"vehicleDailyPriceAfterDiscount":null},"quoteId":null,"tripDetail":null,"vehicleId":1636599},{"accountBalanceDetail":null,"estimatedItemizedDetail":{"discountSavingsText":null,"includedLineItems":[{"description":null,"displayedPerDay":false,"price":{"amount":46.00,"currencyCode":"USD"},"title":"$46 x 1 day","type":"VEHICLE_DAILY_TOTAL"}],"nonIncludedLineItems":[{"description":"Applies to all drivers under 25 years old","displayedPerDay":false,"price":null,"title":"Young driver fee","type":"YOUNG_DRIVER"},{"description":"Includes liability insurance and physical damage protection options; you’ll select a plan when you’re checking out","displayedPerDay":false,"price":null,"title":"Protection plan","type":"PROTECTION"},{"description":"This helps us run the Turo platform","displayedPerDay":false,"price":null,"title":"Trip fee","type":"TRIP_FEE"}],"priceDisplayType":"DAILY_WITH_EST_TOTAL","totalTripPrice":{"amount":46.00,"currencyCode":"USD"},"totalTripPriceBeforeDiscount":null,"vehicleDailyPrice":{"amount":46.00,"currencyCode":"USD"},"vehicleDailyPriceAfterDiscount":null},"quoteId":null,"tripDetail":null,"vehicleId":1908403},{"accountBalanceDetail":null,"estimatedItemizedDetail":{"discountSavingsText":null,"includedLineItems":[{"description":null,"displayedPerDay":false,"price":{"amount":49.00,"currencyCode":"USD"},"title":"$49 x 1 day","type":"VEHICLE_DAILY_TOTAL"}],"nonIncludedLineItems":[{"description":"Applies to all drivers under 25 years old","displayedPerDay":false,"price":null,"title":"Young driver fee","type":"YOUNG_DRIVER"},{"description":"Includes liability insurance and physical damage protection options; you’ll select a plan when you’re checking out","displayedPerDay":false,"price":null,"title":"Protection plan","type":"PROTECTION"},{"description":"This helps us run the Turo platform","displayedPerDay":false,"price":null,"title":"Trip fee","type":"TRIP_FEE"}],"priceDisplayType":"DAILY_WITH_EST_TOTAL","totalTripPrice":{"amount":49.00,"currencyCode":"USD"},"totalTripPriceBeforeDiscount":null,"vehicleDailyPrice":{"amount":49.00,"currencyCode":"USD"},"vehicleDailyPriceAfterDiscount":null},"quoteId":null,"tripDetail":null,"vehicleId":1721050},{"accountBalanceDetail":null,"estimatedItemizedDetail":{"discountSavingsText":null,"includedLineItems":[{"description":null,"displayedPerDay":false,"price":{"amount":71.00,"currencyCode":"USD"},"title":"$71 x 1 day","type":"VEHICLE_DAILY_TOTAL"}],"nonIncludedLineItems":[{"description":"Applies to all drivers under 25 years old","displayedPerDay":false,"price":null,"title":"Young driver fee","type":"YOUNG_DRIVER"},{"description":"Includes liability insurance and physical damage protection options; you’ll select a plan when you’re checking out","displayedPerDay":false,"price":null,"title":"Protection plan","type":"PROTECTION"},{"description":"This helps us run the Turo platform","displayedPerDay":false,"price":null,"title":"Trip fee","type":"TRIP_FEE"}],"priceDisplayType":"DAILY_WITH_EST_TOTAL","totalTripPrice":{"amount":71.00,"currencyCode":"USD"},"totalTripPriceBeforeDiscount":null,"vehicleDailyPrice":{"amount":71.00,"currencyCode":"USD"},"vehicleDailyPriceAfterDiscount":null},"quoteId":null,"tripDetail":null,"vehicleId":1946322},{"accountBalanceDetail":null,"estimatedItemizedDetail":{"discountSavingsText":null,"includedLineItems":[{"description":null,"displayedPerDay":false,"price":{"amount":45.00,"currencyCode":"USD"},"title":"$45 x 1 day","type":"VEHICLE_DAILY_TOTAL"}],"nonIncludedLineItems":[{"description":"Applies to all drivers under 25 years old","displayedPerDay":false,"price":null,"title":"Young driver fee","type":"YOUNG_DRIVER"},{"description":"Includes liability insurance and physical damage protection options; you’ll select a plan when you’re checking out","displayedPerDay":false,"price":null,"title":"Protection plan","type":"PROTECTION"},{"description":"This helps us run the Turo platform","displayedPerDay":false,"price":null,"title":"Trip fee","type":"TRIP_FEE"}],"priceDisplayType":"DAILY_WITH_EST_TOTAL","totalTripPrice":{"amount":45.00,"currencyCode":"USD"},"totalTripPriceBeforeDiscount":null,"vehicleDailyPrice":{"amount":45.00,"currencyCode":"USD"},"vehicleDailyPriceAfterDiscount":null},"quoteId":null,"tripDetail":null,"vehicleId":1877088},{"accountBalanceDetail":null,"estimatedItemizedDetail":{"discountSavingsText":null,"includedLineItems":[{"description":null,"displayedPerDay":false,"price":{"amount":54.00,"currencyCode":"USD"},"title":"$54 x 1 day","type":"VEHICLE_DAILY_TOTAL"}],"nonIncludedLineItems":[{"description":"Applies to all drivers under 25 years old","displayedPerDay":false,"price":null,"title":"Young driver fee","type":"YOUNG_DRIVER"},{"description":"Includes liability insurance and physical damage protection options; you’ll select a plan when you’re checking out","displayedPerDay":false,"price":null,"title":"Protection plan","type":"PROTECTION"},{"description":"This helps us run the Turo platform","displayedPerDay":false,"price":null,"title":"Trip fee","type":"TRIP_FEE"}],"priceDisplayType":"DAILY_WITH_EST_TOTAL","totalTripPrice":{"amount":54.00,"currencyCode":"USD"},"totalTripPriceBeforeDiscount":null,"vehicleDailyPrice":{"amount":54.00,"currencyCode":"USD"},"vehicleDailyPriceAfterDiscount":null},"quoteId":null,"tripDetail":null,"vehicleId":1950579},{"accountBalanceDetail":null,"estimatedItemizedDetail":{"discountSavingsText":null,"includedLineItems":[{"description":null,"displayedPerDay":false,"price":{"amount":55.00,"currencyCode":"USD"},"title":"$55 x 1 day","type":"VEHICLE_DAILY_TOTAL"}],"nonIncludedLineItems":[{"description":"Applies to all drivers under 25 years old","displayedPerDay":false,"price":null,"title":"Young driver fee","type":"YOUNG_DRIVER"},{"description":"Includes liability insurance and physical damage protection options; you’ll select a plan when you’re checking out","displayedPerDay":false,"price":null,"title":"Protection plan","type":"PROTECTION"},{"description":"This helps us run the Turo platform","displayedPerDay":false,"price":null,"title":"Trip fee","type":"TRIP_FEE"}],"priceDisplayType":"DAILY_WITH_EST_TOTAL","totalTripPrice":{"amount":55.00,"currencyCode":"USD"},"totalTripPriceBeforeDiscount":null,"vehicleDailyPrice":{"amount":55.00,"currencyCode":"USD"},"vehicleDailyPriceAfterDiscount":null},"quoteId":null,"tripDetail":null,"vehicleId":737469},{"accountBalanceDetail":null,"estimatedItemizedDetail":{"discountSavingsText":null,"includedLineItems":[{"description":null,"displayedPerDay":false,"price":{"amount":104.00,"currencyCode":"USD"},"title":"$104 x 1 day","type":"VEHICLE_DAILY_TOTAL"}],"nonIncludedLineItems":[{"description":"Applies to all drivers under 25 years old","displayedPerDay":false,"price":null,"title":"Young driver fee","type":"YOUNG_DRIVER"},{"description":"Includes liability insurance and physical damage protection options; you’ll select a plan when you’re checking out","displayedPerDay":false,"price":null,"title":"Protection plan","type":"PROTECTION"},{"description":"This helps us run the Turo platform","displayedPerDay":false,"price":null,"title":"Trip fee","type":"TRIP_FEE"}],"priceDisplayType":"DAILY_WITH_EST_TOTAL","totalTripPrice":{"amount":104.00,"currencyCode":"USD"},"totalTripPriceBeforeDiscount":null,"vehicleDailyPrice":{"amount":104.00,"currencyCode":"USD"},"vehicleDailyPriceAfterDiscount":null},"quoteId":null,"tripDetail":null,"vehicleId":1572739},{"accountBalanceDetail":null,"estimatedItemizedDetail":{"discountSavingsText":null,"includedLineItems":[{"description":null,"displayedPerDay":false,"price":{"amount":90.00,"currencyCode":"USD"},"title":"$90 x 1 day","type":"VEHICLE_DAILY_TOTAL"}],"nonIncludedLineItems":[{"description":"Applies to all drivers under 25 years old","displayedPerDay":false,"price":null,"title":"Young driver fee","type":"YOUNG_DRIVER"},{"description":"Includes liability insurance and physical damage protection options; you’ll select a plan when you’re checking out","displayedPerDay":false,"price":null,"title":"Protection plan","type":"PROTECTION"},{"description":"This helps us run the Turo platform","displayedPerDay":false,"price":null,"title":"Trip fee","type":"TRIP_FEE"}],"priceDisplayType":"DAILY_WITH_EST_TOTAL","totalTripPrice":{"amount":90.00,"currencyCode":"USD"},"totalTripPriceBeforeDiscount":null,"vehicleDailyPrice":{"amount":90.00,"currencyCode":"USD"},"vehicleDailyPriceAfterDiscount":null},"quoteId":null,"tripDetail":null,"vehicleId":1786234},{"accountBalanceDetail":null,"estimatedItemizedDetail":{"discountSavingsText":null,"includedLineItems":[{"description":null,"displayedPerDay":false,"price":{"amount":45.00,"currencyCode":"USD"},"title":"$45 x 1 day","type":"VEHICLE_DAILY_TOTAL"}],"nonIncludedLineItems":[{"description":"Applies to all drivers under 25 years old","displayedPerDay":false,"price":null,"title":"Young driver fee","type":"YOUNG_DRIVER"},{"description":"Includes liability insurance and physical damage protection options; you’ll select a plan when you’re checking out","displayedPerDay":false,"price":null,"title":"Protection plan","type":"PROTECTION"},{"description":"This helps us run the Turo platform","displayedPerDay":false,"price":null,"title":"Trip fee","type":"TRIP_FEE"}],"priceDisplayType":"DAILY_WITH_EST_TOTAL","totalTripPrice":{"amount":45.00,"currencyCode":"USD"},"totalTripPriceBeforeDiscount":null,"vehicleDailyPrice":{"amount":45.00,"currencyCode":"USD"},"vehicleDailyPriceAfterDiscount":null},"quoteId":null,"tripDetail":null,"vehicleId":1616974},{"accountBalanceDetail":null,"estimatedItemizedDetail":{"discountSavingsText":null,"includedLineItems":[{"description":null,"displayedPerDay":false,"price":{"amount":140.00,"currencyCode":"USD"},"title":"$140 x 1 day","type":"VEHICLE_DAILY_TOTAL"}],"nonIncludedLineItems":[{"description":"Applies to all drivers under 25 years old","displayedPerDay":false,"price":null,"title":"Young driver fee","type":"YOUNG_DRIVER"},{"description":"Includes liability insurance and physical damage protection options; you’ll select a plan when you’re checking out","displayedPerDay":false,"price":null,"title":"Protection plan","type":"PROTECTION"},{"description":"This helps us run the Turo platform","displayedPerDay":false,"price":null,"title":"Trip fee","type":"TRIP_FEE"}],"priceDisplayType":"DAILY_WITH_EST_TOTAL","totalTripPrice":{"amount":140.00,"currencyCode":"USD"},"totalTripPriceBeforeDiscount":null,"vehicleDailyPrice":{"amount":140.00,"currencyCode":"USD"},"vehicleDailyPriceAfterDiscount":null},"quoteId":null,"tripDetail":null,"vehicleId":1461256},{"accountBalanceDetail":null,"estimatedItemizedDetail":{"discountSavingsText":null,"includedLineItems":[{"description":null,"displayedPerDay":false,"price":{"amount":62.00,"currencyCode":"USD"},"title":"$62 x 1 day","type":"VEHICLE_DAILY_TOTAL"}],"nonIncludedLineItems":[{"description":"Applies to all drivers under 25 years old","displayedPerDay":false,"price":null,"title":"Young driver fee","type":"YOUNG_DRIVER"},{"description":"Includes liability insurance and physical damage protection options; you’ll select a plan when you’re checking out","displayedPerDay":false,"price":null,"title":"Protection plan","type":"PROTECTION"},{"description":"This helps us run the Turo platform","displayedPerDay":false,"price":null,"title":"Trip fee","type":"TRIP_FEE"}],"priceDisplayType":"DAILY_WITH_EST_TOTAL","totalTripPrice":{"amount":62.00,"currencyCode":"USD"},"totalTripPriceBeforeDiscount":null,"vehicleDailyPrice":{"amount":62.00,"currencyCode":"USD"},"vehicleDailyPriceAfterDiscount":null},"quoteId":null,"tripDetail":null,"vehicleId":1747133},{"accountBalanceDetail":null,"estimatedItemizedDetail":{"discountSavingsText":null,"includedLineItems":[{"description":null,"displayedPerDay":false,"price":{"amount":50.00,"currencyCode":"USD"},"title":"$50 x 1 day","type":"VEHICLE_DAILY_TOTAL"}],"nonIncludedLineItems":[{"description":"Applies to all drivers under 25 years old","displayedPerDay":false,"price":null,"title":"Young driver fee","type":"YOUNG_DRIVER"},{"description":"Includes liability insurance and physical damage protection options; you’ll select a plan when you’re checking out","displayedPerDay":false,"price":null,"title":"Protection plan","type":"PROTECTION"},{"description":"This helps us run the Turo platform","displayedPerDay":false,"price":null,"title":"Trip fee","type":"TRIP_FEE"}],"priceDisplayType":"DAILY_WITH_EST_TOTAL","totalTripPrice":{"amount":50.00,"currencyCode":"USD"},"totalTripPriceBeforeDiscount":null,"vehicleDailyPrice":{"amount":50.00,"currencyCode":"USD"},"vehicleDailyPriceAfterDiscount":null},"quoteId":null,"tripDetail":null,"vehicleId":1534186},{"accountBalanceDetail":null,"estimatedItemizedDetail":{"discountSavingsText":null,"includedLineItems":[{"description":null,"displayedPerDay":false,"price":{"amount":92.00,"currencyCode":"USD"},"title":"$92 x 1 day","type":"VEHICLE_DAILY_TOTAL"}],"nonIncludedLineItems":[{"description":"Applies to all drivers under 25 years old","displayedPerDay":false,"price":null,"title":"Young driver fee","type":"YOUNG_DRIVER"},{"description":"Includes liability insurance and physical damage protection options; you’ll select a plan when you’re checking out","displayedPerDay":false,"price":null,"title":"Protection plan","type":"PROTECTION"},{"description":"This helps us run the Turo platform","displayedPerDay":false,"price":null,"title":"Trip fee","type":"TRIP_FEE"}],"priceDisplayType":"DAILY_WITH_EST_TOTAL","totalTripPrice":{"amount":92.00,"currencyCode":"USD"},"totalTripPriceBeforeDiscount":null,"vehicleDailyPrice":{"amount":92.00,"currencyCode":"USD"},"vehicleDailyPriceAfterDiscount":null},"quoteId":null,"tripDetail":null,"vehicleId":1891789},{"accountBalanceDetail":null,"estimatedItemizedDetail":{"discountSavingsText":null,"includedLineItems":[{"description":null,"displayedPerDay":false,"price":{"amount":90.00,"currencyCode":"USD"},"title":"$90 x 1 day","type":"VEHICLE_DAILY_TOTAL"}],"nonIncludedLineItems":[{"description":"Applies to all drivers under 25 years old","displayedPerDay":false,"price":null,"title":"Young driver fee","type":"YOUNG_DRIVER"},{"description":"Includes liability insurance and physical damage protection options; you’ll select a plan when you’re checking out","displayedPerDay":false,"price":null,"title":"Protection plan","type":"PROTECTION"},{"description":"This helps us run the Turo platform","displayedPerDay":false,"price":null,"title":"Trip fee","type":"TRIP_FEE"}],"priceDisplayType":"DAILY_WITH_EST_TOTAL","totalTripPrice":{"amount":90.00,"currencyCode":"USD"},"totalTripPriceBeforeDiscount":null,"vehicleDailyPrice":{"amount":90.00,"currencyCode":"USD"},"vehicleDailyPriceAfterDiscount":null},"quoteId":null,"tripDetail":null,"vehicleId":1701021},{"accountBalanceDetail":null,"estimatedItemizedDetail":{"discountSavingsText":null,"includedLineItems":[{"description":null,"displayedPerDay":false,"price":{"amount":50.00,"currencyCode":"USD"},"title":"$50 x 1 day","type":"VEHICLE_DAILY_TOTAL"}],"nonIncludedLineItems":[{"description":"Applies to all drivers under 25 years old","displayedPerDay":false,"price":null,"title":"Young driver fee","type":"YOUNG_DRIVER"},{"description":"Includes liability insurance and physical damage protection options; you’ll select a plan when you’re checking out","displayedPerDay":false,"price":null,"title":"Protection plan","type":"PROTECTION"},{"description":"This helps us run the Turo platform","displayedPerDay":false,"price":null,"title":"Trip fee","type":"TRIP_FEE"}],"priceDisplayType":"DAILY_WITH_EST_TOTAL","totalTripPrice":{"amount":50.00,"currencyCode":"USD"},"totalTripPriceBeforeDiscount":null,"vehicleDailyPrice":{"amount":50.00,"currencyCode":"USD"},"vehicleDailyPriceAfterDiscount":null},"quoteId":null,"tripDetail":null,"vehicleId":1874142},{"accountBalanceDetail":null,"estimatedItemizedDetail":{"discountSavingsText":null,"includedLineItems":[{"description":null,"displayedPerDay":false,"price":{"amount":39.00,"currencyCode":"USD"},"title":"$39 x 1 day","type":"VEHICLE_DAILY_TOTAL"}],"nonIncludedLineItems":[{"description":"Applies to all drivers under 25 years old","displayedPerDay":false,"price":null,"title":"Young driver fee","type":"YOUNG_DRIVER"},{"description":"Includes liability insurance and physical damage protection options; you’ll select a plan when you’re checking out","displayedPerDay":false,"price":null,"title":"Protection plan","type":"PROTECTION"},{"description":"This helps us run the Turo platform","displayedPerDay":false,"price":null,"title":"Trip fee","type":"TRIP_FEE"}],"priceDisplayType":"DAILY_WITH_EST_TOTAL","totalTripPrice":{"amount":39.00,"currencyCode":"USD"},"totalTripPriceBeforeDiscount":null,"vehicleDailyPrice":{"amount":39.00,"currencyCode":"USD"},"vehicleDailyPriceAfterDiscount":null},"quoteId":null,"tripDetail":null,"vehicleId":1443205}]}